sashite_cell/__init__.py
sashite_cell/coordinate.py
sashite_cell/formatter.py
sashite_cell/parser.py
sashite_cell/py.typed
sashite_cell-2.0.0.dist-info/METADATA
sashite_cell-2.0.0.dist-info/WHEEL
sashite_cell-2.0.0.dist-info/licenses/LICENSE
sashite_cell-2.0.0.dist-info/RECORD
