Metadata-Version: 2.4
Name: sashite-cell
Version: 2.0.0
Summary: CELL (Coordinate Encoding for Layered Locations) implementation for Python
Project-URL: Homepage, https://github.com/sashite/cell.py
Project-URL: Documentation, https://github.com/sashite/cell.py#readme
Project-URL: Repository, https://github.com/sashite/cell.py
Project-URL: Specification, https://sashite.dev/specs/cell/1.0.0/
Project-URL: Issues, https://github.com/sashite/cell.py/issues
Author: Cyril Kato
License-Expression: Apache-2.0
License-File: LICENSE
Keywords: board-games,cell,chess,coordinates,game-protocol,multi-dimensional,shogi,xiangqi
Classifier: Development Status :: 5 - Production/Stable
Classifier: Intended Audience :: Developers
Classifier: License :: OSI Approved :: Apache Software License
Classifier: Operating System :: OS Independent
Classifier: Programming Language :: Python :: 3
Classifier: Programming Language :: Python :: 3.12
Classifier: Programming Language :: Python :: 3.13
Classifier: Programming Language :: Python :: 3.14
Classifier: Topic :: Games/Entertainment :: Board Games
Classifier: Topic :: Software Development :: Libraries :: Python Modules
Classifier: Typing :: Typed
Requires-Python: >=3.12
